Zen_STT/__init__.py
zen_stt-0.8.dist-info/licenses/LICENSE
zen_stt-0.8.dist-info/METADATA
zen_stt-0.8.dist-info/WHEEL
zen_stt-0.8.dist-info/top_level.txt
zen_stt-0.8.dist-info/RECORD
